{
  "id": "2026-04-19-github-cangjie-skill",
  "title": "Cangjie Skill: 将书籍知识蒸馏为可执行 Agent Skill",
  "source": "github-trending",
  "source_url": "https://github.com/kangarooking/cangjie-skill",
  "collected_at": "2026-04-19T00:00:00Z",
  "summary": "将书籍方法论蒸馏为 Agent 可调用的 Skill 文件，解决读书后用不起来的痛点。",
  "analysis": {
    "tech_highlights": ["与 nuwa-skill(蒸馏人)/darwin-skill(自进化) 形成完整生态", "提供无需编程的 Skill 生成模板和标准化流程"],
    "relevance_score": 6,
    "score_reason": "知识蒸馏路径有启发性，但偏方法论模板缺工程实现代码"
  },
  "tags": ["prompt-engineering", "knowledge-distillation", "agent-framework"],
  "status": "draft"
}
